cfa_hermes-2.8.1.data/data/sample/hermes/sample_sftp_get1.hermes
cfa_hermes-2.8.1.data/data/sample/hermes/sample_sftp_get2.hermes
cfa_hermes-2.8.1.data/data/sample/hermes/sample_sftp_put1.hermes
cfa_hermes-2.8.1.data/data/sample/hermes/sample_sftp_put2.hermes
cfa_hermes-2.8.1.data/data/sample/hermes/sample_sftp_put3.hermes
cfa_hermes-2.8.1.data/scripts/hcmd.py
cfa_hermes-2.8.1.data/scripts/hermesd.py
hermes/__init__.py
hermes/_version.py
hermes/connection.py
hermes/exception.py
hermes/ftp.py
hermes/sftp.py
hermes/thread.py
cfa_hermes-2.8.1.dist-info/METADATA
cfa_hermes-2.8.1.dist-info/WHEEL
cfa_hermes-2.8.1.dist-info/top_level.txt
cfa_hermes-2.8.1.dist-info/RECORD
