Metadata-Version: 2.1
Name: cfa-hermes
Version: 2.8.1
Summary: file tranfer monitor protocols ftp, sftp
Home-page: https://github.com/cfauchard/hermes
Author: Christophe Fauchard
Author-email: christophe.fauchard@gmail.com
License: GPLV3
Platform: UNKNOWN
Requires-Dist: cfa-zeus (>=3.3.0.b1)
Requires-Dist: paramiko
